shell/__init__.py
libpyshell-0.5.0.dist-info/LICENSE
libpyshell-0.5.0.dist-info/METADATA
libpyshell-0.5.0.dist-info/WHEEL
libpyshell-0.5.0.dist-info/top_level.txt
libpyshell-0.5.0.dist-info/RECORD
