Metadata-Version: 2.2
Name: libPyshell
Version: 0.5.0
Summary: Support for writing shell scripts in Python
Home-page: https://github.com/skogsbaer/libPyshell
Author: Stefan Wehr
Author-email: stefan.wehr@gmail.com
Requires-Python: >=3.9
License-File: LICENSE
Dynamic: author
Dynamic: author-email
Dynamic: description
Dynamic: description-content-type
Dynamic: home-page
Dynamic: requires-python
Dynamic: summary
